{
    "24": "Scott Base",
    "35": "South Island",
    "36": "South Island",
    "37": "South Island",
    "43": "Wellington",
    "44": "Wellington",
    "45": "Wellington/Hutt Valley",
    "49": "Wellington",
    "92": "Auckland",
    "93": "Auckland/Waiheke Island",
    "95": "Auckland",
    "96": "Auckland",
    "98": "Auckland",
    "99": "Auckland",
    "320": "Gore/Edendale",
    "321": "Invercargill/Stewart Island/Rakiura",
    "322": "Otautau",
    "323": "Riverton/Winton",
    "324": "Tokanui/Lumsden/Te Anau",
    "325": "South Island",
    "326": "South Island",
    "327": "South Island",
    "328": "South Island",
    "329": "South Island",
    "330": "Ashburton/Akaroa/Chatham Islands",
    "331": "Rangiora/Amberley/Culverden/Darfield/Cheviot/Kaikoura",
    "332": "Christchurch",
    "333": "Christchurch",
    "334": "Christchurch/Rolleston",
    "335": "Christchurch",
    "336": "South Island",
    "337": "Christchurch",
    "338": "Christchurch",
    "339": "South Island",
    "340": "South Island",
    "341": "Balclutha/Milton",
    "342": "South Island",
    "343": "Oamaru/Mount Cook/Twizel/Kurow",
    "344": "Queenstown/Cromwell/Alexandra/Wanaka/Ranfurly/Roxburgh",
    "345": "Dunedin/Queenstown",
    "346": "Dunedin/Palmerston",
    "347": "Dunedin",
    "348": "Dunedin/Lawrence/Mosgiel",
    "349": "South Island",
    "352": "Murchison/Takaka/Motueka",
    "354": "Nelson",
    "357": "Blenheim",
    "361": "Timaru",
    "368": "Timaru/Waimate/Fairlie",
    "369": "Geraldine",
    "373": "Greymouth",
    "375": "Hokitika/Franz Josef Glacier/Fox Glacier/Haast",
    "376": "Greymouth",
    "378": "Westport",
    "390": "Ashburton",
    "391": "South Island",
    "392": "South Island",
    "393": "South Island",
    "394": "Christchurch/Invercargill",
    "395": "Dunedin/Timaru",
    "396": "Christchurch",
    "397": "Christchurch",
    "398": "Christchurch/Blenheim/Nelson",
    "399": "South Island",
    "423": "Wellington/Porirua/Tawa",
    "429": "Paraparaumu",
    "480": "Wellington",
    "490": "Paraparaumu",
    "627": "Hawera",
    "630": "Featherston",
    "632": "Palmerston North/Marton",
    "634": "Wanganui",
    "635": "Palmerston North City",
    "636": "Levin",
    "637": "Masterton/Dannevirke/Pahiatua",
    "638": "Taihape/Ohakune/Waiouru",
    "675": "New Plymouth/Mokau",
    "676": "New Plymouth/Opunake/Stratford",
    "683": "Napier/Wairoa",
    "684": "Napier City",
    "685": "Waipukurau",
    "686": "Gisborne/Ruatoria",
    "687": "Napier/Hastings",
    "694": "Masterton/Levin",
    "695": "Palmerston North/New Plymouth",
    "696": "Wanganui/New Plymouth",
    "697": "Napier",
    "698": "Gisborne",
    "730": "Whakatane",
    "731": "Whakatane/Opotiki",
    "732": "Whakatane",
    "733": "Rotorua/Taupo",
    "734": "Rotorua",
    "735": "Rotorua",
    "736": "Rotorua",
    "737": "Taupo",
    "738": "Taupo",
    "754": "Tauranga",
    "757": "Tauranga",
    "782": "Hamilton/Huntly",
    "783": "Hamilton",
    "784": "Hamilton",
    "785": "Hamilton",
    "786": "Paeroa/Waihi/Thames/Whangamata",
    "787": "Te Awamutu/Otorohanga/Te Kuiti",
    "788": "Matamata/Putaruru/Morrinsville",
    "789": "Taumarunui",
    "790": "Taupo",
    "792": "Rotorua/Whakatane/Tauranga",
    "793": "Tauranga",
    "795": "Hamilton",
    "796": "Hamilton",
    "923": "Pukekohe",
    "940": "Kaikohe/Kaitaia/Kawakawa",
    "941": "Auckland",
    "942": "Helensville/Warkworth/Hibiscus Coast/Great Barrier Island",
    "943": "Whangarei/Maungaturoto",
    "944": "Auckland",
    "947": "Auckland",
    "948": "Auckland",
    "990": "Warkworth",
    "998": "Whangarei",
    "3409": "Queenstown"
}